blog/__init__.py
blog/admin.py
blog/apps.py
blog/feeds.py
blog/forms.py
blog/models.py
blog/sitemaps.py
blog/tests.py
blog/urls.py
blog/views.py
blog/migrations/0001_initial.py
blog/migrations/0002_auto_20211110_1252.py
blog/migrations/__init__.py
blog/templatetags/__init__.py
blog/templatetags/blog_tags.py
mysite/__init__.py
mysite/asgi.py
mysite/settings.py
mysite/urls.py
mysite/wsgi.py
django_bloggy-1.0.dist-info/LICENSE
django_bloggy-1.0.dist-info/METADATA
django_bloggy-1.0.dist-info/WHEEL
django_bloggy-1.0.dist-info/top_level.txt
django_bloggy-1.0.dist-info/RECORD
